[
  {
    "localidade.id":"11",
    "localidade.nivel.nome":"Unidade da Federação",
    "localidade.nome":"Rondônia",
    "serie.2014":"1748531",
    "serie.2015":"1768204",
    "serie.2016":"1787279",
    "serie.2017":"1805788",
    "serie.2018":"1757589",
    "serie.2019":"1777225",
    "serie.2020":"1796460",
    "serie.2021":"1815278",
    "serie.2024":"1746227"
  },
  {
    "localidade.id":"12",
    "localidade.nivel.nome":"Unidade da Federação",
    "localidade.nome":"Acre",
    "serie.2014":"790101",
    "serie.2015":"803513",
    "serie.2016":"816687",
    "serie.2017":"829619",
    "serie.2018":"869265",
    "serie.2019":"881935",
    "serie.2020":"894470",
    "serie.2021":"906876",
    "serie.2024":"880631"
  },
  {
    "localidade.id":"13",
    "localidade.nivel.nome":"Unidade da Federação",
    "localidade.nome":"Amazonas",
    "serie.2014":"3873743",
    "serie.2015":"3938336",
    "serie.2016":"4001667",
    "serie.2017":"4063614",
    "serie.2018":"4080611",
    "serie.2019":"4144597",
    "serie.2020":"4207714",
    "serie.2021":"4269995",
    "serie.2024":"4281209"
  },
  {
    "localidade.id":"14",
    "localidade.nivel.nome":"Unidade da Federação",
    "localidade.nome":"Roraima",
    "serie.2014":"496936",
    "serie.2015":"505665",
    "serie.2016":"514229",
    "serie.2017":"522636",
    "serie.2018":"576568",
    "serie.2019":"605761",
    "serie.2020":"631181",
    "serie.2021":"652713",
    "serie.2024":"716793"
  },
  {
    "localidade.id":"15",
    "localidade.nivel.nome":"Unidade da Federação",
    "localidade.nome":"Pará",
    "serie.2014":"8073924",
    "serie.2015":"8175113",
    "serie.2016":"8272724",
    "serie.2017":"8366628",
    "serie.2018":"8513497",
    "serie.2019":"8602865",
    "serie.2020":"8690745",
    "serie.2021":"8777124",
    "serie.2024":"8664306"
  },
  {
    "localidade.id":"16",
    "localidade.nivel.nome":"Unidade da Federação",
    "localidade.nome":"Amapá",
    "serie.2014":"750912",
    "serie.2015":"766679",
    "serie.2016":"782295",
    "serie.2017":"797722",
    "serie.2018":"829494",
    "serie.2019":"845731",
    "serie.2020":"861773",
    "serie.2021":"877613",
    "serie.2024":"802837"
  },
  {
    "localidade.id":"17",
    "localidade.nivel.nome":"Unidade da Federação",
    "localidade.nome":"Tocantins",
    "serie.2014":"1496880",
    "serie.2015":"1515126",
    "serie.2016":"1532902",
    "serie.2017":"1550194",
    "serie.2018":"1555229",
    "serie.2019":"1572866",
    "serie.2020":"1590248",
    "serie.2021":"1607363",
    "serie.2024":"1577342"
  },
  {
    "localidade.id":"21",
    "localidade.nivel.nome":"Unidade da Federação",
    "localidade.nome":"Maranhão",
    "serie.2014":"6850884",
    "serie.2015":"6904241",
    "serie.2016":"6954036",
    "serie.2017":"7000229",
    "serie.2018":"7035055",
    "serie.2019":"7075181",
    "serie.2020":"7114598",
    "serie.2021":"7153262",
    "serie.2024":"7010960"
  },
  {
    "localidade.id":"22",
    "localidade.nivel.nome":"Unidade da Federação",
    "localidade.nome":"Piauí",
    "serie.2014":"3194718",
    "serie.2015":"3204028",
    "serie.2016":"3212180",
    "serie.2017":"3219257",
    "serie.2018":"3264531",
    "serie.2019":"3273227",
    "serie.2020":"3281480",
    "serie.2021":"3289290",
    "serie.2024":"3375646"
  },
  {
    "localidade.id":"23",
    "localidade.nivel.nome":"Unidade da Federação",
    "localidade.nome":"Ceará",
    "serie.2014":"8842791",
    "serie.2015":"8904459",
    "serie.2016":"8963663",
    "serie.2017":"9020460",
    "serie.2018":"9075649",
    "serie.2019":"9132078",
    "serie.2020":"9187103",
    "serie.2021":"9240580",
    "serie.2024":"9233656"
  },
  {
    "localidade.id":"24",
    "localidade.nivel.nome":"Unidade da Federação",
    "localidade.nome":"Rio Grande do Norte",
    "serie.2014":"3408510",
    "serie.2015":"3442175",
    "serie.2016":"3474998",
    "serie.2017":"3507003",
    "serie.2018":"3479010",
    "serie.2019":"3506853",
    "serie.2020":"3534165",
    "serie.2021":"3560903",
    "serie.2024":"3446071"
  },
  {
    "localidade.id":"25",
    "localidade.nivel.nome":"Unidade da Federação",
    "localidade.nome":"Paraíba",
    "serie.2014":"3943885",
    "serie.2015":"3972202",
    "serie.2016":"3999415",
    "serie.2017":"4025558",
    "serie.2018":"3996496",
    "serie.2019":"4018127",
    "serie.2020":"4039277",
    "serie.2021":"4059905",
    "serie.2024":"4145040"
  },
  {
    "localidade.id":"26",
    "localidade.nivel.nome":"Unidade da Federação",
    "localidade.nome":"Pernambuco",
    "serie.2014":"9277727",
    "serie.2015":"9345173",
    "serie.2016":"9410336",
    "serie.2017":"9473266",
    "serie.2018":"9496294",
    "serie.2019":"9557071",
    "serie.2020":"9616621",
    "serie.2021":"9674793",
    "serie.2024":"9539029"
  },
  {
    "localidade.id":"27",
    "localidade.nivel.nome":"Unidade da Federação",
    "localidade.nome":"Alagoas",
    "serie.2014":"3321730",
    "serie.2015":"3340932",
    "serie.2016":"3358963",
    "serie.2017":"3375823",
    "serie.2018":"3322820",
    "serie.2019":"3337357",
    "serie.2020":"3351543",
    "serie.2021":"3365351",
    "serie.2024":"3220104"
  },
  {
    "localidade.id":"28",
    "localidade.nivel.nome":"Unidade da Federação",
    "localidade.nome":"Sergipe",
    "serie.2014":"2219574",
    "serie.2015":"2242937",
    "serie.2016":"2265779",
    "serie.2017":"2288116",
    "serie.2018":"2278308",
    "serie.2019":"2298696",
    "serie.2020":"2318822",
    "serie.2021":"2338474",
    "serie.2024":"2291077"
  },
  {
    "localidade.id":"29",
    "localidade.nivel.nome":"Unidade da Federação",
    "localidade.nome":"Bahia",
    "serie.2014":"15126371",
    "serie.2015":"15203334",
    "serie.2016":"15276566",
    "serie.2017":"15344447",
    "serie.2018":"14812617",
    "serie.2019":"14873064",
    "serie.2020":"14930634",
    "serie.2021":"14985284",
    "serie.2024":"14850513"
  },
  {
    "localidade.id":"31",
    "localidade.nivel.nome":"Unidade da Federação",
    "localidade.nome":"Minas Gerais",
    "serie.2014":"20734097",
    "serie.2015":"20869101",
    "serie.2016":"20997560",
    "serie.2017":"21119536",
    "serie.2018":"21040662",
    "serie.2019":"21168791",
    "serie.2020":"21292666",
    "serie.2021":"21411923",
    "serie.2024":"21322691"
  },
  {
    "localidade.id":"32",
    "localidade.nivel.nome":"Unidade da Federação",
    "localidade.nome":"Espírito Santo",
    "serie.2014":"3885049",
    "serie.2015":"3929911",
    "serie.2016":"3973697",
    "serie.2017":"4016356",
    "serie.2018":"3972388",
    "serie.2019":"4018650",
    "serie.2020":"4064052",
    "serie.2021":"4108508",
    "serie.2024":"4102129"
  },
  {
    "localidade.id":"33",
    "localidade.nivel.nome":"Unidade da Federação",
    "localidade.nome":"Rio de Janeiro",
    "serie.2014":"16461173",
    "serie.2015":"16550024",
    "serie.2016":"16635996",
    "serie.2017":"16718956",
    "serie.2018":"17159960",
    "serie.2019":"17264943",
    "serie.2020":"17366189",
    "serie.2021":"17463349",
    "serie.2024":"17219679"
  },
  {
    "localidade.id":"35",
    "localidade.nivel.nome":"Unidade da Federação",
    "localidade.nome":"São Paulo",
    "serie.2014":"44035304",
    "serie.2015":"44396484",
    "serie.2016":"44749699",
    "serie.2017":"45094866",
    "serie.2018":"45538936",
    "serie.2019":"45919049",
    "serie.2020":"46289333",
    "serie.2021":"46649132",
    "serie.2024":"45973194"
  },
  {
    "localidade.id":"41",
    "localidade.nivel.nome":"Unidade da Federação",
    "localidade.nome":"Paraná",
    "serie.2014":"11081692",
    "serie.2015":"11163018",
    "serie.2016":"11242720",
    "serie.2017":"11320892",
    "serie.2018":"11348937",
    "serie.2019":"11433957",
    "serie.2020":"11516840",
    "serie.2021":"11597484",
    "serie.2024":"11824665"
  },
  {
    "localidade.id":"42",
    "localidade.nivel.nome":"Unidade da Federação",
    "localidade.nome":"Santa Catarina",
    "serie.2014":"6727148",
    "serie.2015":"6819190",
    "serie.2016":"6910553",
    "serie.2017":"7001161",
    "serie.2018":"7075494",
    "serie.2019":"7164788",
    "serie.2020":"7252502",
    "serie.2021":"7338473",
    "serie.2024":"8058441"
  },
  {
    "localidade.id":"43",
    "localidade.nivel.nome":"Unidade da Federação",
    "localidade.nome":"Rio Grande do Sul",
    "serie.2014":"11207274",
    "serie.2015":"11247972",
    "serie.2016":"11286500",
    "serie.2017":"11322895",
    "serie.2018":"11329605",
    "serie.2019":"11377239",
    "serie.2020":"11422973",
    "serie.2021":"11466630",
    "serie.2024":"11229915"
  },
  {
    "localidade.id":"50",
    "localidade.nivel.nome":"Unidade da Federação",
    "localidade.nome":"Mato Grosso do Sul",
    "serie.2014":"2619657",
    "serie.2015":"2651235",
    "serie.2016":"2682386",
    "serie.2017":"2713147",
    "serie.2018":"2748023",
    "serie.2019":"2778986",
    "serie.2020":"2809394",
    "serie.2021":"2839188",
    "serie.2024":"2901895"
  },
  {
    "localidade.id":"51",
    "localidade.nivel.nome":"Unidade da Federação",
    "localidade.nome":"Mato Grosso",
    "serie.2014":"3224357",
    "serie.2015":"3265486",
    "serie.2016":"3305531",
    "serie.2017":"3344544",
    "serie.2018":"3441998",
    "serie.2019":"3484466",
    "serie.2020":"3526220",
    "serie.2021":"3567234",
    "serie.2024":"3836399"
  },
  {
    "localidade.id":"52",
    "localidade.nivel.nome":"Unidade da Federação",
    "localidade.nome":"Goiás",
    "serie.2014":"6523222",
    "serie.2015":"6610681",
    "serie.2016":"6695855",
    "serie.2017":"6778772",
    "serie.2018":"6921161",
    "serie.2019":"7018354",
    "serie.2020":"7113540",
    "serie.2021":"7206589",
    "serie.2024":"7350483"
  },
  {
    "localidade.id":"53",
    "localidade.nivel.nome":"Unidade da Federação",
    "localidade.nome":"Distrito Federal",
    "serie.2014":"2852372",
    "serie.2015":"2914830",
    "serie.2016":"2977216",
    "serie.2017":"3039444",
    "serie.2018":"2974703",
    "serie.2019":"3015268",
    "serie.2020":"3055149",
    "serie.2021":"3094325",
    "serie.2024":"2982818"
  }
]